chucknorris/__init__.py
chucknorris/main.py
meme/__init__.py
meme/main.py
memeapiwrappers-0.0.2.dist-info/LICENSE
memeapiwrappers-0.0.2.dist-info/METADATA
memeapiwrappers-0.0.2.dist-info/WHEEL
memeapiwrappers-0.0.2.dist-info/top_level.txt
memeapiwrappers-0.0.2.dist-info/RECORD
