Metadata-Version: 2.1
Name: memeapiwrappers
Version: 0.0.2
Summary: A big api wrapper which wrappers most of the funny apis :)
Home-page: https://github.com/ProjectsWithPython/memeapiwrappers
Author: Haider Ali
Author-email: ali075398@gmail.com
License: UNKNOWN
Project-URL: Bug Tracker, https://github.com/ProjectsWithPython/memeapiwrappers/issues
Platform: UNKNOWN
Classifier: Programming Language :: Python :: 3
Classifier: License :: OSI Approved :: MIT License
Classifier: Operating System :: OS Independent
Requires-Python: >=3.6
License-File: LICENSE
